<?xml version="1.0" encoding="utf-8" ?>
<dwsync>
<file name="Module.php" server="ftp.neocreative.com.br" local="130220983540000000" remote="130220983540000000" Dst="2" />
<file name="ViewSetup.php" server="ftp.neocreative.com.br" local="130220983540000000" remote="130220983540000000" Dst="2" />
<file name="ActionSetup.php" server="ftp.neocreative.com.br" local="130220983540000000" remote="130220983540000000" Dst="2" />
<file name="LayoutSetup.php" server="ftp.neocreative.com.br" local="130220983540000000" remote="130220983540000000" Dst="2" />
<file name="ActionSetup.php" server="ftp.neocreative.com.br/subdominios/cbc/" local="130220983540000000" remote="130335904020000000" Dst="2" />
<file name="LayoutSetup.php" server="ftp.neocreative.com.br/subdominios/cbc/" local="130220983540000000" remote="130335904020000000" Dst="2" />
<file name="Module.php" server="ftp.neocreative.com.br/subdominios/cbc/" local="130220983540000000" remote="130335904020000000" Dst="2" />
<file name="ViewSetup.php" server="ftp.neocreative.com.br/subdominios/cbc/" local="130220983540000000" remote="130335904020000000" Dst="2" />
<file name="ActionSetup.php" server="ftp.neocreative.com.br/subdominios/ecommerce2014/" local="130220983540000000" remote="130389694240000000" Dst="1" />
<file name="LayoutSetup.php" server="ftp.neocreative.com.br/subdominios/ecommerce2014/" local="130389643580290396" remote="130389694240000000" Dst="1" />
<file name="Module.php" server="ftp.neocreative.com.br/subdominios/ecommerce2014/" local="130220983540000000" remote="130389694250000000" Dst="1" />
<file name="ViewSetup.php" server="ftp.neocreative.com.br/subdominios/ecommerce2014/" local="130220983540000000" remote="130389694250000000" Dst="1" />
</dwsync>